setup.cfg
setup.py
python_timer.egg-info/PKG-INFO
python_timer.egg-info/SOURCES.txt
python_timer.egg-info/dependency_links.txt
python_timer.egg-info/not-zip-safe
python_timer.egg-info/top_level.txt
timer/__init__.py
timer/timer.py