Metadata-Version: 1.1
Name: python-timer
Version: 0.22
Summary: A wrapper for long-running tasks that iterate over many things, printing friendly 'percentage done' messages to standard error.
Home-page: https://github.com/gabegaster/python-timer
Author: Gabe Gaster
Author-email: gabe@datascopeanalytics.com
License: MIT
Download-URL: https://github.com/gabegaster/python-timer/archives/master
Platform: UNKNOWN
Classifier: Intended Audience :: Developers
Classifier: Operating System :: OS Independent
Classifier: Topic :: Software Development
